fixify/__init__.py
fixify/core.py
fixify-0.1.1.dist-info/LICENSE
fixify-0.1.1.dist-info/METADATA
fixify-0.1.1.dist-info/WHEEL
fixify-0.1.1.dist-info/top_level.txt
fixify-0.1.1.dist-info/RECORD
