Metadata-Version: 2.1
Name: fixify
Version: 0.1.1
Summary: Terminal AI for Code Explanation & Correction
Author: YellowForest
License: MIT
Classifier: Programming Language :: Python :: 3
Classifier: License :: OSI Approved :: MIT License
Classifier: Operating System :: OS Independent
Classifier: Intended Audience :: Developers
Classifier: Intended Audience :: Science/Research
Classifier: Topic :: Scientific/Engineering :: Mathematics
Requires-Python: >=3.6
License-File: LICENSE
Requires-Dist: pandas
Requires-Dist: numpy
Requires-Dist: IPython
Requires-Dist: together
Requires-Dist: Click
